sphinxcli/__init__.py
sphinxcli/__main__.py
sphinxcli/build.py
sphinxcli/check.py
sphinxcli/clean.py
sphinxcli/config.py
sphinxcli/defaults.py
sphinxcli/dirs.py
sphinxcli/exec.py
sphinxcli/findfile.py
sphinxcli/help.py
sphinxcli/logging.py
sphinxcli/myst-extensions.toml
sphinxcli/parse.py
sphinxcli/py.typed
sphinxcli/pyproject.py
sphinxcli/repl.py
sphinxcli/sphinx-extensions.toml
sphinxcli/sphinx-themes.toml
sphinxcli/sphinxconf.py
sphinxcli/toml.py
sphinxcli/tool_config.py
sphinxcli/types.py
sphinxcli/use.py
sphinxcli/util.py
sphinxcli-0.1.1.dist-info/entry_points.txt
sphinxcli-0.1.1.dist-info/LICENSE
sphinxcli-0.1.1.dist-info/WHEEL
sphinxcli-0.1.1.dist-info/METADATA
sphinxcli-0.1.1.dist-info/RECORD
