Metadata-Version: 2.1
Name: sphinxcli
Version: 0.1.1
Summary: 
License: Apache-2.0
Author: Simon Kennedy
Author-email: sffjunkie+code@gmail.com
Requires-Python: >=3.10,<4.0
Classifier: License :: OSI Approved :: Apache Software License
Classifier: Programming Language :: Python :: 3
Classifier: Programming Language :: Python :: 3.10
Requires-Dist: Sphinx (>=5.1.1,<6.0.0)
Requires-Dist: click (>=8.1.3,<9.0.0)
Requires-Dist: click-repl (>=0.2.0,<0.3.0)
Requires-Dist: docutils (>=0.19,<0.20)
Requires-Dist: furo (>=2022.9.15,<2023.0.0)
Requires-Dist: rich (>=12.5.1,<13.0.0)
Requires-Dist: rich-click (>=1.5.2,<2.0.0)
Requires-Dist: tomlkit (>=0.11.4,<0.12.0)
Requires-Dist: typing-extensions (>=4.3.0,<5.0.0)
Requires-Dist: xdg (>=5.1.1,<6.0.0)
